<?xml version="1.0"?>
<MethodSetup Method="MLP::XS_26_56_0_n2n">
  <GeneralInfo>
    <Info name="TMVA Release" value="4.2.1 [262657]"/>
    <Info name="ROOT Release" value="6.06/02 [394754]"/>
    <Info name="Creator" value="mouginot"/>
    <Info name="Date" value="Thu Feb 23 07:18:06 2017"/>
    <Info name="Host" value="Linux e300.chtc.wisc.edu 2.6.32-642.13.1.el6.x86_64 #1 SMP Tue Jan 10 11:22:50 CST 2017 x86_64 x86_64 x86_64 GNU/Linux"/>
    <Info name="Dir" value="/mnt/gluster/mouginot/TRU_MOX_XS/Generate"/>
    <Info name="Training events" value="198960"/>
    <Info name="TrainingTime" value="9.71031066e+03"/>
    <Info name="AnalysisType" value="Regression"/>
  </GeneralInfo>
  <Options>
    <Option name="NCycles" modified="Yes">20000</Option>
    <Option name="HiddenLayers" modified="Yes">N,N</Option>
    <Option name="NeuronType" modified="Yes">tanh</Option>
    <Option name="RandomSeed" modified="No">1</Option>
    <Option name="EstimatorType" modified="No">MSE</Option>
    <Option name="NeuronInputType" modified="No">sum</Option>
    <Option name="V" modified="Yes">False</Option>
    <Option name="VerbosityLevel" modified="No">Default</Option>
    <Option name="VarTransform" modified="Yes">Norm</Option>
    <Option name="H" modified="Yes">False</Option>
    <Option name="CreateMVAPdfs" modified="No">False</Option>
    <Option name="IgnoreNegWeightsInTraining" modified="No">False</Option>
    <Option name="TrainingMethod" modified="Yes">BFGS</Option>
    <Option name="LearningRate" modified="No">2.000000e-02</Option>
    <Option name="DecayRate" modified="No">1.000000e-02</Option>
    <Option name="TestRate" modified="Yes">6</Option>
    <Option name="EpochMonitoring" modified="No">False</Option>
    <Option name="Sampling" modified="Yes">3.000000e-01</Option>
    <Option name="SamplingEpoch" modified="Yes">8.000000e-01</Option>
    <Option name="SamplingImportance" modified="No">1.000000e+00</Option>
    <Option name="SamplingTraining" modified="No">True</Option>
    <Option name="SamplingTesting" modified="No">False</Option>
    <Option name="ResetStep" modified="No">50</Option>
    <Option name="Tau" modified="No">3.000000e+00</Option>
    <Option name="BPMode" modified="No">sequential</Option>
    <Option name="BatchSize" modified="No">-1</Option>
    <Option name="ConvergenceImprove" modified="Yes">1.000000e-06</Option>
    <Option name="ConvergenceTests" modified="Yes">15</Option>
    <Option name="UseRegulator" modified="Yes">False</Option>
    <Option name="UpdateLimit" modified="No">10000</Option>
    <Option name="CalculateErrors" modified="No">False</Option>
    <Option name="WeightRange" modified="No">1.000000e+00</Option>
  </Options>
  <Variables NVar="17">
    <Variable VarIndex="0" Expression="235U" Label="235U" Title="235U" Unit="IsotopicFraction" Internal="235U" Type="F" Min="1.71346517e-06" Max="1.92414057e-02"/>
    <Variable VarIndex="1" Expression="238U" Label="238U" Title="238U" Unit="IsotopicFraction" Internal="238U" Type="F" Min="7.85399854e-01" Max="9.68733251e-01"/>
    <Variable VarIndex="2" Expression="237Np" Label="237Np" Title="237Np" Unit="IsotopicFraction" Internal="237Np" Type="F" Min="1.63990119e-08" Max="1.97294168e-04"/>
    <Variable VarIndex="3" Expression="238Pu" Label="238Pu" Title="238Pu" Unit="IsotopicFraction" Internal="238Pu" Type="F" Min="4.69728775e-07" Max="3.96428024e-03"/>
    <Variable VarIndex="4" Expression="239Pu" Label="239Pu" Title="239Pu" Unit="IsotopicFraction" Internal="239Pu" Type="F" Min="2.15940680e-02" Max="1.89886928e-01"/>
    <Variable VarIndex="5" Expression="240Pu" Label="240Pu" Title="240Pu" Unit="IsotopicFraction" Internal="240Pu" Type="F" Min="1.54567579e-06" Max="3.95636074e-02"/>
    <Variable VarIndex="6" Expression="241Pu" Label="241Pu" Title="241Pu" Unit="IsotopicFraction" Internal="241Pu" Type="F" Min="3.22813172e-08" Max="7.04628276e-03"/>
    <Variable VarIndex="7" Expression="242Pu" Label="242Pu" Title="242Pu" Unit="IsotopicFraction" Internal="242Pu" Type="F" Min="1.58277174e-07" Max="1.98803633e-03"/>
    <Variable VarIndex="8" Expression="241Am" Label="241Am" Title="241Am" Unit="IsotopicFraction" Internal="241Am" Type="F" Min="3.13082671e-10" Max="7.48056592e-03"/>
    <Variable VarIndex="9" Expression="242Amm" Label="242Amm" Title="242Amm" Unit="IsotopicFraction" Internal="242Amm" Type="F" Min="1.34159976e-07" Max="1.16249369e-02"/>
    <Variable VarIndex="10" Expression="243Am" Label="243Am" Title="243Am" Unit="IsotopicFraction" Internal="243Am" Type="F" Min="2.04390229e-08" Max="1.99559363e-04"/>
    <Variable VarIndex="11" Expression="242Cm" Label="242Cm" Title="242Cm" Unit="IsotopicFraction" Internal="242Cm" Type="F" Min="1.48285639e-09" Max="1.93909858e-04"/>
    <Variable VarIndex="12" Expression="243Cm" Label="243Cm" Title="243Cm" Unit="IsotopicFraction" Internal="243Cm" Type="F" Min="9.09117492e-09" Max="1.97552916e-04"/>
    <Variable VarIndex="13" Expression="244Cm" Label="244Cm" Title="244Cm" Unit="IsotopicFraction" Internal="244Cm" Type="F" Min="2.46570231e-09" Max="1.97112051e-04"/>
    <Variable VarIndex="14" Expression="245Cm" Label="245Cm" Title="245Cm" Unit="IsotopicFraction" Internal="245Cm" Type="F" Min="9.47205692e-09" Max="1.97873349e-04"/>
    <Variable VarIndex="15" Expression="246Cm" Label="246Cm" Title="246Cm" Unit="IsotopicFraction" Internal="246Cm" Type="F" Min="2.33963915e-09" Max="1.98596885e-04"/>
    <Variable VarIndex="16" Expression="Time" Label="Time" Title="Time" Unit="seconds" Internal="Time" Type="F" Min="0.00000000e+00" Max="1.89328320e+08"/>
  </Variables>
  <Spectators NSpec="0"/>
  <Classes NClass="1">
    <Class Name="Regression" Index="0"/>
  </Classes>
  <Targets NTrgt="1">
    <Target TargetIndex="0" Expression="XS_26_56_0_n2n" Label="XS_26_56_0_n2n" Title="XS_26_56_0_n2n" Unit="" Internal="XS_26_56_0_n2n" Type="F" Min="1.61127427e-05" Max="1.06659922e-04"/>
  </Targets>
  <Transformations NTransformations="1">
    <Transform Name="Normalize">
      <Selection>
        <Input NInputs="18">
          <Input Type="Variable" Label="235U" Expression="235U"/>
          <Input Type="Variable" Label="238U" Expression="238U"/>
          <Input Type="Variable" Label="237Np" Expression="237Np"/>
          <Input Type="Variable" Label="238Pu" Expression="238Pu"/>
          <Input Type="Variable" Label="239Pu" Expression="239Pu"/>
          <Input Type="Variable" Label="240Pu" Expression="240Pu"/>
          <Input Type="Variable" Label="241Pu" Expression="241Pu"/>
          <Input Type="Variable" Label="242Pu" Expression="242Pu"/>
          <Input Type="Variable" Label="241Am" Expression="241Am"/>
          <Input Type="Variable" Label="242Amm" Expression="242Amm"/>
          <Input Type="Variable" Label="243Am" Expression="243Am"/>
          <Input Type="Variable" Label="242Cm" Expression="242Cm"/>
          <Input Type="Variable" Label="243Cm" Expression="243Cm"/>
          <Input Type="Variable" Label="244Cm" Expression="244Cm"/>
          <Input Type="Variable" Label="245Cm" Expression="245Cm"/>
          <Input Type="Variable" Label="246Cm" Expression="246Cm"/>
          <Input Type="Variable" Label="Time" Expression="Time"/>
          <Input Type="Target" Label="XS_26_56_0_n2n" Expression="XS_26_56_0_n2n"/>
        </Input>
        <Output NOutputs="18">
          <Output Type="Variable" Label="235U" Expression="235U"/>
          <Output Type="Variable" Label="238U" Expression="238U"/>
          <Output Type="Variable" Label="237Np" Expression="237Np"/>
          <Output Type="Variable" Label="238Pu" Expression="238Pu"/>
          <Output Type="Variable" Label="239Pu" Expression="239Pu"/>
          <Output Type="Variable" Label="240Pu" Expression="240Pu"/>
          <Output Type="Variable" Label="241Pu" Expression="241Pu"/>
          <Output Type="Variable" Label="242Pu" Expression="242Pu"/>
          <Output Type="Variable" Label="241Am" Expression="241Am"/>
          <Output Type="Variable" Label="242Amm" Expression="242Amm"/>
          <Output Type="Variable" Label="243Am" Expression="243Am"/>
          <Output Type="Variable" Label="242Cm" Expression="242Cm"/>
          <Output Type="Variable" Label="243Cm" Expression="243Cm"/>
          <Output Type="Variable" Label="244Cm" Expression="244Cm"/>
          <Output Type="Variable" Label="245Cm" Expression="245Cm"/>
          <Output Type="Variable" Label="246Cm" Expression="246Cm"/>
          <Output Type="Variable" Label="Time" Expression="Time"/>
          <Output Type="Target" Label="XS_26_56_0_n2n" Expression="XS_26_56_0_n2n"/>
        </Output>
      </Selection>
      <Class ClassIndex="0">
        <Ranges>
          <Range Index="0" Min="1.7134651670858148e-06" Max="1.9241405650973320e-02"/>
          <Range Index="1" Min="7.8539985418319702e-01" Max="9.6873325109481812e-01"/>
          <Range Index="2" Min="1.6399011926182538e-08" Max="1.9729416817426682e-04"/>
          <Range Index="3" Min="4.6972877498774324e-07" Max="3.9642802439630032e-03"/>
          <Range Index="4" Min="2.1594068035483360e-02" Max="1.8988692760467529e-01"/>
          <Range Index="5" Min="1.5456757864740212e-06" Max="3.9563607424497604e-02"/>
          <Range Index="6" Min="3.2281317174920332e-08" Max="7.0462827570736408e-03"/>
          <Range Index="7" Min="1.5827717447791656e-07" Max="1.9880363252013922e-03"/>
          <Range Index="8" Min="3.1308267089968922e-10" Max="7.4805659241974354e-03"/>
          <Range Index="9" Min="1.3415997557331139e-07" Max="1.1624936945736408e-02"/>
          <Range Index="10" Min="2.0439022918594674e-08" Max="1.9955936295446008e-04"/>
          <Range Index="11" Min="1.4828563932312022e-09" Max="1.9390985835343599e-04"/>
          <Range Index="12" Min="9.0911749239808159e-09" Max="1.9755291577894241e-04"/>
          <Range Index="13" Min="2.4657023089957875e-09" Max="1.9711205095518380e-04"/>
          <Range Index="14" Min="9.4720569165929192e-09" Max="1.9787334895227104e-04"/>
          <Range Index="15" Min="2.3396391490848600e-09" Max="1.9859688472934067e-04"/>
          <Range Index="16" Min="0.0000000000000000e+00" Max="1.8932832000000000e+08"/>
          <Range Index="17" Min="1.6112742741825059e-05" Max="1.0665992158465087e-04"/>
        </Ranges>
      </Class>
    </Transform>
  </Transformations>
  <MVAPdfs/>
  <Weights>
    <Layout NLayers="4">
      <Layer Index="0" NNeurons="18">
        <Neuron NSynapses="17">
          -4.2084127225123397e-01 1.7974372381193837e+00 8.7718298654893201e-01 1.7043360794930242e+00 -1.8952223447044714e+00 -1.4003877313092283e+00 -8.0230869171631636e-01 1.8780476904283174e+00 -1.3842074170381953e+00 -1.1400308405279125e+00 -1.5241044831153285e+00 -5.8159631341098350e-01 -1.2311743926086607e+00 -4.2972234705989470e-01 -4.2924139929381405e-01 4.2151378675904910e-01 -4.7275123620585624e-01 
        </Neuron>
        <Neuron NSynapses="17">
          1.7777375104231807e+00 4.0886459028223471e-01 1.6843910686245878e+00 -2.1421816542336264e-01 -8.0254044785707357e-01 4.3905180261792515e-01 1.0911314460724607e-01 -1.0540534464238858e+00 -3.7117558549611190e-01 1.4222856359421776e+00 -9.2952803891903546e-01 -1.8628675500294205e+00 1.3066297599099225e-01 5.9749557392481412e-01 1.3000384152230562e+00 6.4863232396444412e-02 1.2576655540090034e-01 
        </Neuron>
        <Neuron NSynapses="17">
          2.8725902108239587e-01 -2.4194473600368285e-01 -1.4481136436572637e+00 1.6489543407196101e+00 -1.4796927385216256e+00 1.1096959387714540e+00 1.3478782144031130e+00 9.1974961782953568e-01 1.8466103346924976e+00 1.1409828050676143e+00 -7.0863128324882996e-01 -1.4442158734757102e+00 6.9088890223069410e-01 -6.8967853980229768e-02 1.5520713605699972e+00 1.3487390143893172e+00 1.5318480333608557e+00 
        </Neuron>
        <Neuron NSynapses="17">
          1.4404288629021411e+00 -1.5029508474968098e+00 1.4504813516296657e+00 -1.7079286460959391e+00 -1.1146869908955233e+00 -1.2674499893621607e+00 -1.4534951897025006e+00 1.4155345516369273e+00 5.5049304277028721e-01 -1.7798277926547479e+00 4.2062550162607443e-01 -5.5126867087349030e-01 6.0500926898863139e-01 1.5164659364757336e+00 -1.5885815410476253e-01 2.4418509161676952e-01 -8.6784389114840610e-01 
        </Neuron>
        <Neuron NSynapses="17">
          7.9248914388602532e-01 -1.0013605298089476e+00 -9.4588732003659370e-01 -1.5282958480728595e+00 6.6605599775259394e-01 1.3932702088994555e+00 1.4155304640938533e+00 -4.3280318345848273e-01 -1.8466478246923419e+00 -1.8312980524105194e+00 8.9018977416318967e-01 4.9764103606434190e-01 1.9359699683249647e+00 6.3936247483138442e-01 1.2741991280527474e+00 -1.1004758032561541e+00 -1.0862101827608004e+00 
        </Neuron>
        <Neuron NSynapses="17">
          -4.9890891212251716e-02 1.2111735316133134e+00 -1.0018649404371816e+00 -1.5171147594957539e+00 -1.9607055208244206e+00 -1.5562184937203899e-01 2.0967340414673716e-01 1.6651605030487593e+00 -1.5735921626125853e+00 -9.6383587455663122e-01 1.6455902630008896e+00 -9.4074271909585327e-01 -1.6316648750065674e+00 -1.7077706955181002e+00 2.1748102820731882e-01 -1.8326522127357678e+00 -1.3240880652106921e+00 
        </Neuron>
        <Neuron NSynapses="17">
          8.9418439878411504e-01 1.8575519443783612e+00 -9.7075716999637751e-01 1.6973287423645238e+00 -1.3559327363076510e+00 -8.5767620511633103e-01 3.2463789228802337e-01 3.2503103780004305e-01 -1.9171163453172095e+00 5.3203710574214129e-02 3.6359099400003786e-01 4.0290749022699757e-01 -1.5735596801042468e+00 1.4631954914598249e+00 3.9510045435560004e-01 -7.1303059265884927e-01 1.1298082229385173e+00 
        </Neuron>
        <Neuron NSynapses="17">
          -8.7839199579536009e-01 -1.4607509034998611e+00 2.2425535519789325e-01 -2.9851300367039030e-01 1.4659788786273824e+00 8.1245045723822762e-01 2.9209743144055317e-01 -3.7147985542414069e-01 1.0587846926312459e-01 -1.9031757160612863e+00 1.0766220717784531e+00 1.0401802622366421e-01 -1.8710362592479013e+00 3.8110177036125836e-01 -1.2417727768724680e+00 1.2710565551383574e-01 1.2974513023220868e+00 
        </Neuron>
        <Neuron NSynapses="17">
          1.9989257820904063e+00 -1.7590721924675961e+00 5.8336260960713404e-01 1.6595413385708833e+00 1.0743156557145739e+00 1.1137736834374352e-01 -1.0204021067212345e+00 -5.9858771488487360e-02 -1.5134350463727515e+00 1.3060061028645860e+00 1.3493031307066163e+00 -3.6283647002823616e-01 -6.2447774609162765e-01 -1.5999405937873803e-01 -1.2334277003129843e+00 7.5917788696520538e-01 2.0564714412848812e+00 
        </Neuron>
        <Neuron NSynapses="17">
          -4.3748229077436540e-01 -7.7450288737183171e-01 3.1462479212668543e-01 1.0921869349499573e+00 3.2751491317843195e-01 1.1696981007079019e+00 -1.1563102974414956e+00 1.5247597003325624e+00 5.8305792212865792e-01 3.4868911989427764e-01 5.9136036909008249e-01 1.1033027897276264e+00 -8.4895878233318900e-01 -6.1486542136611622e-01 1.5579224209001794e+00 -1.2756284103840927e+00 -4.3701670790094260e-01 
        </Neuron>
        <Neuron NSynapses="17">
          1.5110601201106419e+00 8.3137258405604331e-01 -3.6534572763234330e-01 1.4124845038662004e+00 1.5514732365587360e+00 -1.7857577148284007e+00 7.8350074348626231e-01 -2.3892802319738109e-02 4.0846146218626189e-01 -1.8271616013167207e+00 -1.4885737801445980e+00 1.0675462406888183e+00 1.5876549486509555e+00 -1.7471796238273771e+00 3.1687238917458019e-02 -7.3695410901524905e-01 3.1177333569512355e-01 
        </Neuron>
        <Neuron NSynapses="17">
          1.8538034985972855e+00 -3.1851922511174829e-01 -3.6044536161642327e-01 -1.0072300722021474e+00 7.2781566349108318e-01 1.6814255953017627e+00 1.3115917952287746e+00 3.5940405735205638e-01 -7.9727442164125450e-01 -2.1379858505387350e+00 1.0948866553894583e+00 5.2977497471514745e-01 -1.4495374161363062e+00 -9.6005646433597824e-01 3.4492073884127789e-01 2.1657623484737543e-01 -1.6883494231033445e+00 
        </Neuron>
        <Neuron NSynapses="17">
          1.7531631275989503e+00 9.0300052618888027e-01 -4.1844630290454099e-01 -6.7932411252682845e-02 1.2910531680904256e+00 1.0451127133305109e+00 8.5434358186033699e-01 -5.6645552913946629e-02 -1.8983075225562080e+00 -1.0945783475857696e+00 1.7446053200302658e+00 1.4610676950817620e+00 7.2172080976753372e-01 -7.3708725925434121e-02 1.8813618804341423e+00 -1.3309385562032987e+00 -9.1634526429837682e-01 
        </Neuron>
        <Neuron NSynapses="17">
          2.4777845393185272e-02 -1.3973982776386769e+00 1.0071863078835790e+00 1.7379317618875003e+00 -1.4584191267414115e+00 9.0035337686314054e-01 9.3380165550420766e-02 -1.8504662684404773e+00 -1.1216758630821204e+00 8.7330568641897444e-01 7.3824369322935332e-02 8.8146367034444417e-01 -1.2889208850194882e+00 1.3977151347272443e+00 -1.5813463844722577e+00 7.8581488258667131e-01 2.2272354455673213e-01 
        </Neuron>
        <Neuron NSynapses="17">
          -1.3495950183428771e+00 -1.3135921675486675e+00 -1.8792792356297556e+00 -3.8331811069362398e-01 -2.1358608120503804e+00 -1.5039149548008173e+00 -1.5715075726852241e+00 1.8930452930728781e-01 -1.0374538357191758e+00 -1.7238228312597546e+00 1.4065379310924035e+00 -7.0671434961529156e-01 2.0453909068392711e-02 -1.2122549564383405e+00 3.9056792124112727e-01 1.7321358356945493e+00 1.4416580622274624e+00 
        </Neuron>
        <Neuron NSynapses="17">
          -6.7630287356725327e-01 -1.3119929381719162e+00 -9.5926423750094758e-01 -8.5917681981986671e-01 -1.9185097850372383e+00 3.4205931567616327e-01 5.7153415868671920e-01 1.8714671828784208e+00 -2.7988604961972802e-01 8.5167230380239364e-02 -4.7579788113946986e-01 -1.9411340527266538e+00 1.2268372128860379e+00 9.1771105870968994e-01 -7.5144006202227531e-01 -9.2955343730903017e-01 1.0625656415919000e+00 
        </Neuron>
        <Neuron NSynapses="17">
          1.1937696858042277e+00 6.9509318116304486e-01 -3.2513621308604757e-01 -3.3372432533650176e-01 1.2094977941401248e+00 8.1388581483205791e-01 7.2889620477015027e-01 -4.1307424217460548e-01 2.1830283892699937e-01 -2.5495077107017039e-01 -1.3423090255537351e+00 -6.5968361533051934e-01 -1.5443801754589306e+00 -1.5698057123315940e+00 -1.8059035023604586e+00 2.2907192110501478e+00 -1.4495677291094629e+00 
        </Neuron>
        <Neuron NSynapses="17">
          1.3246402111904207e+00 -1.8815102238861157e+00 6.4892092599537654e-01 -1.3295218978845529e+00 1.2069227650923975e+00 1.0845459559154973e+00 -2.5426265449318430e+00 1.0765875148155613e-01 8.7003213602227336e-01 -1.5442241497247962e+00 -1.7377030192360385e+00 -1.8798111054969959e+00 -5.6585011113005124e-01 2.4373422745923778e+00 -5.3580112148081760e-01 -1.8576137266929982e-01 -1.6566166377568945e+00 
        </Neuron>
      </Layer>
      <Layer Index="1" NNeurons="18">
        <Neuron NSynapses="17">
          -1.2323692158003354e+00 -1.6958681394268080e+00 -8.2845828557680345e-01 -1.5081648481777370e+00 8.5234588757531216e-01 -1.5162846424124894e+00 -1.1327752800906512e+00 1.6494755884421486e+00 5.0276880639470645e-01 -5.4559946271637827e-01 2.0371316525023015e+00 -1.8142255307635577e+00 1.4859420147190632e+00 9.6687285766756637e-01 -1.1565272766605323e+00 -5.8219977592001104e-01 -1.5935357024040817e-01 
        </Neuron>
        <Neuron NSynapses="17">
          -1.0913112512229786e+00 4.7462780154738565e-01 1.9814764720889553e+00 1.3291294705923993e+00 1.6884272726027088e+00 -1.3537442932932673e+00 8.7318186926156094e-01 -2.1037063363613648e+00 5.7828201057311468e-01 -1.7142676199687537e+00 -2.0676645079558340e+00 -4.8825763574645797e-02 1.2967957774291374e+00 3.7644980724849336e-01 9.5076963567256900e-01 3.5870678909086717e-01 -2.0579071627019513e-01 
        </Neuron>
        <Neuron NSynapses="17">
          -6.4311427651084452e-01 1.1896466268025217e-01 1.8928687149655350e+00 -1.4243346511109263e+00 3.7007859933515763e-01 -1.1149528816338961e+00 -5.9490713332302148e-01 1.9296252347147835e-01 -5.1332088820202931e-02 -1.1162737415801289e+00 7.0306170572329563e-01 1.6725754714375616e+00 6.5323909579465533e-01 -9.8206840661917427e-02 -7.2565093286773008e-01 -1.5671909127211932e+00 -1.5863638596815373e+00 
        </Neuron>
        <Neuron NSynapses="17">
          9.1960701604146988e-01 -5.2305549847223054e-01 -1.0163114032838014e+00 3.1016451489537838e-01 -1.8464819540269013e+00 -1.3588787497225008e+00 -1.4581457922265968e+00 8.9036678939803127e-01 -1.2098660918208584e+00 -1.7071513887072034e+00 -4.8103823214507485e-01 -9.5089262707546651e-01 -1.6292878277248297e+00 1.2376547778222122e+00 -1.5611997693889066e+00 -1.2109925432711028e+00 1.5440929057558055e+00 
        </Neuron>
        <Neuron NSynapses="17">
          6.7451935904474170e-01 3.1060883736429812e-01 4.8105196504979714e-02 1.3740926471485724e+00 1.8151626562649312e+00 8.1494864549125223e-01 -1.1332213070289170e+00 -4.9868392327897765e-01 -1.8001299506081245e+00 8.9819622268207033e-01 8.0590699872040494e-01 9.8045933156046872e-02 1.0863828564391107e+00 8.5721254727368990e-01 1.5807392811753789e+00 -1.2965268144888691e+00 1.6375092231260922e+00 
        </Neuron>
        <Neuron NSynapses="17">
          7.7088900996097998e-01 -1.9343041101611518e+00 -2.1100323335374069e-01 -9.2946029524623908e-01 8.6726078032404241e-01 5.8711282618082838e-01 1.0403712937022445e+00 1.8359878869532640e+00 -1.8067565706792413e-01 1.7461810272278258e+00 1.8392489097461968e+00 2.0114076210847551e-01 -1.0927824390367076e+00 1.6154391335945517e+00 -2.0888575383128827e+00 7.1183236753733692e-01 1.6618762829160307e+00 
        </Neuron>
        <Neuron NSynapses="17">
          -4.2081878805624484e-01 -8.1085246019235047e-01 5.2834686443443239e-02 -1.2746787763730687e+00 3.6880351845378456e-01 -2.2241659256914401e+00 3.3178174281449518e-01 -3.7065720103983790e-01 2.0361579464573731e+00 1.1517084477499606e+00 1.9128007269854497e+00 -5.5933058726472085e-01 -3.5015028897196987e-01 3.1076940033910366e-01 1.5759916498501703e+00 -1.6515694804761509e+00 -1.4021768060919217e+00 
        </Neuron>
        <Neuron NSynapses="17">
          -6.9024293199436870e-01 -1.4894422676471661e+00 -1.5616468985533893e+00 -1.8437101145870447e+00 5.6928658284635159e-01 -2.8359739098301417e-01 -1.6996735021660176e+00 -1.8984918354682607e+00 -3.0669944774857932e-01 1.8231910750843121e+00 1.8349991210183729e+00 1.3078184647260578e+00 -6.1207860252617308e-01 -1.7875743677142102e+00 7.0097330011269471e-02 -1.2896076517180948e+00 -1.5279786650014087e+00 
        </Neuron>
        <Neuron NSynapses="17">
          -5.8983628279822997e-01 1.3798464684787211e-02 -1.5818049676381014e+00 1.4938206462998675e+00 1.2771085975955390e+00 8.8883204485009892e-01 -7.2619489031702622e-01 -6.4904085804835010e-01 1.5227544134427644e+00 -5.4910709428284410e-01 2.7256528156907912e-02 1.6066443213413588e+00 1.5159530189084256e+00 -1.0085124591300134e+00 1.6684427368293460e+00 -2.0349971232632056e+00 1.7767250451181076e+00 
        </Neuron>
        <Neuron NSynapses="17">
          1.9642656153851044e+00 -1.7141266877383016e-01 -2.0355086940972111e-01 3.1671307769195767e-01 -5.5347558664307950e-01 8.5138720324920159e-01 1.4622797476221905e-01 -8.6094035597545260e-01 -1.5075302617268775e+00 6.8088835039350698e-03 1.4938114863487635e+00 3.8470993143203891e-01 -7.8739564452223232e-01 -1.7985737887708313e+00 1.7601971772548914e+00 3.1249160747791244e-01 -1.2124340254517161e+00 
        </Neuron>
        <Neuron NSynapses="17">
          -3.8756734196420545e-01 -1.0057410392905688e+00 1.2709328389433558e+00 1.3956868219075802e+00 -7.9319942092960904e-01 -1.5917762298171103e+00 1.6980427625613403e+00 1.0842066045937047e+00 4.9707319629470997e-01 1.7023138289267267e-01 -9.5312324936345239e-01 -1.2359233442288449e+00 1.0660028284522003e+00 3.8212769388221285e-01 2.2982467287358579e-01 -1.7566510138515041e+00 -1.9629230996079452e+00 
        </Neuron>
        <Neuron NSynapses="17">
          -2.0517962653700179e+00 -3.1732808680823393e-01 -1.5837800108065991e+00 2.2428990552617789e-01 -6.6240432443683273e-01 1.2340253457556634e+00 6.2156835378942621e-01 -1.8004033078686439e+00 1.0959919862015834e+00 1.9854255187274441e+00 1.0480925776859000e+00 -4.3689031206915685e-01 -9.0892553073225490e-01 2.1649185606722883e+00 -1.4657316478292384e+00 5.0017291497679461e-01 -1.4572182921599630e+00 
        </Neuron>
        <Neuron NSynapses="17">
          1.1018088925602647e+00 -1.1633132057847528e+00 6.7999265885183818e-02 -1.4801677128752422e-01 3.7853093705161422e-01 -7.0340167148528088e-02 -6.6680528119976890e-01 9.5493729633176083e-01 4.3571324918631049e-01 8.2034059111297863e-01 9.5791041220591833e-01 -1.6863895477471784e+00 1.2022776501506842e+00 -1.8104714572625460e+00 1.1211996683441325e+00 8.3588067016689971e-01 7.6416593283793777e-01 
        </Neuron>
        <Neuron NSynapses="17">
          1.5775704211929951e+00 1.4602887452909585e+00 -2.0165143106257326e+00 -6.6087801571977367e-01 -9.6800964462420391e-01 7.2404797450585967e-01 -1.4993391558466934e-01 -9.9896712664068826e-02 -5.4037153077137845e-01 -4.8619560456072475e-01 -9.8492591333227075e-01 -3.5791483810697983e-01 -1.8485057312017270e+00 -2.8714634185012117e-01 2.9231709223053459e-01 -7.4550774700901690e-01 -1.2977993533803907e+00 
        </Neuron>
        <Neuron NSynapses="17">
          2.8770075001366835e-01 2.4814137919377530e-01 -4.5247921153929205e-01 -1.1720654819135981e+00 1.8133797003524605e+00 -1.5995639088568767e-01 8.2757158108322981e-01 5.8436440254908129e-01 -9.6057405250422234e-01 -8.8701777567811324e-01 -7.5631559983353400e-02 -1.9405010198987498e+00 -8.7130360945800589e-01 -1.0750548069850647e+00 1.0714924523598992e+00 -2.1359023244634696e+00 1.3073073234626218e+00 
        </Neuron>
        <Neuron NSynapses="17">
          1.8871386033342765e+00 1.6031372547056104e+00 1.1782774445580297e+00 7.4563685921356659e-01 1.7379457643521362e-01 -8.1623001476940960e-01 -2.1874810364291530e+00 -1.0072091742085165e+00 -8.8464983639815742e-01 1.4148651472911282e+00 -2.0603966069249464e-03 8.6668421588616887e-02 1.5622968792927150e+00 1.0633900319529836e+00 -1.2648025109659746e+00 4.6427723186644954e-01 -1.5741520990521187e+00 
        </Neuron>
        <Neuron NSynapses="17">
          7.8946178314745552e-01 -1.8291725305592650e+00 1.7953000809834588e-01 -4.1169707946480533e-01 8.8934696501042187e-01 -2.2253025254338596e+00 4.7281630792510493e-01 -1.7893237213811077e+00 2.1253935511231743e-02 1.2836217558092464e+00 -6.0427530304760668e-01 5.3965065309530513e-01 -1.7144691904546796e+00 1.0966683311162477e+00 -5.5429063692174163e-01 7.3069548193580436e-01 -1.7122226644947947e+00 
        </Neuron>
        <Neuron NSynapses="17">
          -9.4702309845690302e-01 1.9348546979893146e+00 -2.0276226230970598e+00 -1.1373307670210000e+00 -7.6613975199754847e-01 2.2496757167531034e+00 1.3506255194578296e+00 1.7301073492682792e+00 -1.9236812358054658e+00 7.5866981158218183e-01 4.6242067683637439e-01 2.8691873636906573e-01 -1.2500322192535058e+00 -1.3818406499250242e+00 3.0665000594556302e-01 -2.2815063379053035e-01 1.8391695422878718e+00 
        </Neuron>
      </Layer>
      <Layer Index="2" NNeurons="18">
        <Neuron NSynapses="1">
          -1.8858823144129875e-02 
        </Neuron>
        <Neuron NSynapses="1">
          -8.0083601381452409e-03 
        </Neuron>
        <Neuron NSynapses="1">
          -3.5268537620093902e-02 
        </Neuron>
        <Neuron NSynapses="1">
          7.8756724292612119e-03 
        </Neuron>
        <Neuron NSynapses="1">
          -7.5454531039127045e-03 
        </Neuron>
        <Neuron NSynapses="1">
          -1.1142326366650983e+00 
        </Neuron>
        <Neuron NSynapses="1">
          1.8721831765707523e-02 
        </Neuron>
        <Neuron NSynapses="1">
          1.3021954398478126e-02 
        </Neuron>
        <Neuron NSynapses="1">
          -2.7769631047274798e-02 
        </Neuron>
        <Neuron NSynapses="1">
          9.4124692178205443e-03 
        </Neuron>
        <Neuron NSynapses="1">
          6.4531817097563445e-04 
        </Neuron>
        <Neuron NSynapses="1">
          8.6651534598993340e-03 
        </Neuron>
        <Neuron NSynapses="1">
          -3.3399111398809980e-02 
        </Neuron>
        <Neuron NSynapses="1">
          -8.9098631274468505e-03 
        </Neuron>
        <Neuron NSynapses="1">
          3.5549111415191562e-03 
        </Neuron>
        <Neuron NSynapses="1">
          -2.5587820940876190e-02 
        </Neuron>
        <Neuron NSynapses="1">
          -2.0982750354904532e-03 
        </Neuron>
        <Neuron NSynapses="1">
          8.5367513393441441e-01 
        </Neuron>
      </Layer>
      <Layer Index="3" NNeurons="1">
        <Neuron NSynapses="0"/>
      </Layer>
    </Layout>
  </Weights>
</MethodSetup>
